src/__init__.py
src/aws.py
src/parsers.py
aws_dashboard-1.0.2.dist-info/LICENCE
aws_dashboard-1.0.2.dist-info/METADATA
aws_dashboard-1.0.2.dist-info/WHEEL
aws_dashboard-1.0.2.dist-info/entry_points.txt
aws_dashboard-1.0.2.dist-info/top_level.txt
aws_dashboard-1.0.2.dist-info/RECORD
