Metadata-Version: 2.1
Name: aws-dashboard
Version: 1.0.2
Summary: Small EC2 and RDS monitor and control tool
Home-page: https://github.com/hntirgeam/aws-dashboard
Author: hntirgeam
Author-email: me@example.com
License: MIT
Platform: UNKNOWN
Classifier: License :: OSI Approved :: MIT License
Classifier: Programming Language :: Python
Classifier: Programming Language :: Python :: 3
Classifier: Programming Language :: Python :: 3.6
Classifier: Programming Language :: Python :: Implementation :: CPython
Classifier: Programming Language :: Python :: Implementation :: PyPy
Requires-Python: >=3.8
Requires-Dist: boto3
Requires-Dist: click
Requires-Dist: colorama
Requires-Dist: python-dateutil
Requires-Dist: tabulate
